[
    {
        "id": 1773485441801,
        "name": "Ionia Yone",
        "nameIsAuto": true,
        "level": 8,
        "gold": 9999,
        "board": {
            "A1": null,
            "A2": null,
            "A3": null,
            "A4": null,
            "A5": null,
            "A6": null,
            "A7": null,
            "B1": null,
            "B2": null,
            "B3": null,
            "B4": null,
            "B5": null,
            "B6": null,
            "B7": null,
            "C1": null,
            "C2": null,
            "C3": null,
            "C4": null,
            "C5": null,
            "C6": null,
            "C7": null,
            "D1": null,
            "D2": null,
            "D3": null,
            "D4": null,
            "D5": null,
            "D6": null,
            "D7": null
        },
        "bench": [
            null,
            null,
            null,
            null,
            null,
            null,
            null,
            null,
            null
        ],
        "teamPlan": [
            "Yone",
            "Ahri",
            "Wukong",
            "Kennen",
            "Sett",
            "Neeko",
            "Yasuo",
            "Shen"
        ],
        "targetTeam": [],
        "autoGenerateTeam": false,
        "unlocks": [
            "Kennen",
            "Yone",
            "Sett"
        ]
    },
    {
        "id": 1773485452486,
        "name": "Warden Kalista",
        "nameIsAuto": true,
        "level": 8,
        "gold": 44,
        "board": {
            "D1": null,
            "D2": null,
            "D3": null,
            "D4": null,
            "D5": null,
            "D6": null,
            "D7": null,
            "C1": null,
            "C2": null,
            "C3": null,
            "C4": null,
            "C5": null,
            "C6": null,
            "C7": null,
            "B1": null,
            "B2": null,
            "B3": null,
            "B4": null,
            "B5": null,
            "B6": null,
            "B7": null,
            "A1": null,
            "A2": null,
            "A3": null,
            "A4": null,
            "A5": null,
            "A6": null,
            "A7": null
        },
        "bench": [
            null,
            null,
            null,
            null,
            null,
            null,
            null,
            null,
            null
        ],
        "teamPlan": [
            "Yorick",
            "Gwen",
            "Loris",
            "Braum",
            "Kalista",
            "Seraphine",
            "Thresh",
            "Ambessa",
            "Ornn",
            "Fiddlesticks"
        ],
        "targetTeam": [
            "Viego",
            "Yorick",
            "Gwen",
            "Loris",
            "Braum",
            "Kalista",
            "Seraphine",
            "Thresh",
            "Ambessa"
        ],
        "autoGenerateTeam": false,
        "unlocks": [
            "Yorick",
            "Gwen",
            "Kalista",
            "Thresh"
        ]
    },
    {
        "id": 1773485588177,
        "name": "Demacia Lux",
        "nameIsAuto": true,
        "level": 8,
        "gold": 44,
        "board": {
            "D1": null,
            "D2": null,
            "D3": null,
            "D4": null,
            "D5": null,
            "D6": null,
            "D7": null,
            "C1": null,
            "C2": null,
            "C3": null,
            "C4": null,
            "C5": null,
            "C6": null,
            "C7": null,
            "B1": null,
            "B2": null,
            "B3": null,
            "B4": null,
            "B5": null,
            "B6": null,
            "B7": null,
            "A1": null,
            "A2": null,
            "A3": null,
            "A4": null,
            "A5": null,
            "A6": null,
            "A7": null
        },
        "bench": [
            null,
            null,
            null,
            null,
            null,
            null,
            null,
            null,
            null
        ],
        "teamPlan": [
            "Lux",
            "Garen",
            "Galio",
            "Swain",
            "Taric",
            "Poppy",
            "Xin Zhao",
            "Jarvan IV",
            "Sona",
            "Lissandra"
        ],
        "targetTeam": [
            "Lux",
            "Garen",
            "Galio",
            "Swain",
            "Zilean",
            "Taric",
            "Poppy",
            "Xin Zhao",
            "Jarvan IV",
            "Sona"
        ],
        "autoGenerateTeam": false,
        "unlocks": [
            "Poppy",
            "Galio"
        ]
    },
    {
        "id": 1773485621288,
        "name": "Yordle Veigar",
        "nameIsAuto": true,
        "level": 8,
        "gold": 44,
        "board": {
            "D1": null,
            "D2": null,
            "D3": null,
            "D4": null,
            "D5": null,
            "D6": null,
            "D7": null,
            "C1": null,
            "C2": null,
            "C3": null,
            "C4": null,
            "C5": null,
            "C6": null,
            "C7": null,
            "B1": null,
            "B2": null,
            "B3": null,
            "B4": null,
            "B5": null,
            "B6": null,
            "B7": null,
            "A1": null,
            "A2": null,
            "A3": null,
            "A4": null,
            "A5": null,
            "A6": null,
            "A7": null
        },
        "bench": [
            null,
            null,
            null,
            null,
            null,
            null,
            null,
            null,
            null
        ],
        "teamPlan": [
            "Veigar",
            "Kennen",
            "Ziggs",
            "Fizz",
            "Swain",
            "Kobuko & Yuumi",
            "Poppy",
            "Teemo",
            "Rumble"
        ],
        "targetTeam": [],
        "autoGenerateTeam": false,
        "unlocks": [
            "Poppy",
            "Kennen",
            "Kobuko & Yuumi",
            "Fizz",
            "Veigar",
            "Ziggs"
        ]
    },
    {
        "id": 1773485640528,
        "name": "Bruiser Kai'Sa",
        "nameIsAuto": true,
        "level": 8,
        "gold": 44,
        "board": {
            "D1": null,
            "D2": null,
            "D3": null,
            "D4": null,
            "D5": null,
            "D6": null,
            "D7": null,
            "C1": null,
            "C2": null,
            "C3": null,
            "C4": null,
            "C5": null,
            "C6": null,
            "C7": null,
            "B1": null,
            "B2": null,
            "B3": null,
            "B4": null,
            "B5": null,
            "B6": null,
            "B7": null,
            "A1": null,
            "A2": null,
            "A3": null,
            "A4": null,
            "A5": null,
            "A6": null,
            "A7": null
        },
        "bench": [
            null,
            null,
            null,
            null,
            null,
            null,
            null,
            null,
            null
        ],
        "teamPlan": [
            "Kai'Sa",
            "Rift Herald",
            "Volibear",
            "Swain",
            "Ziggs",
            "Wukong",
            "Kobuko & Yuumi",
            "Cho'Gath",
            "Kog'Maw"
        ],
        "targetTeam": [],
        "autoGenerateTeam": false,
        "unlocks": [
            "Kobuko & Yuumi",
            "Kai'Sa",
            "Rift Herald",
            "Volibear",
            "Ziggs"
        ]
    },
    {
        "id": 1773485662504,
        "name": "Void Ambessa",
        "nameIsAuto": true,
        "level": 8,
        "gold": 44,
        "board": {
            "D1": null,
            "D2": null,
            "D3": null,
            "D4": null,
            "D5": null,
            "D6": null,
            "D7": null,
            "C1": null,
            "C2": null,
            "C3": null,
            "C4": null,
            "C5": null,
            "C6": null,
            "C7": null,
            "B1": null,
            "B2": null,
            "B3": null,
            "B4": null,
            "B5": null,
            "B6": null,
            "B7": null,
            "A1": null,
            "A2": null,
            "A3": null,
            "A4": null,
            "A5": null,
            "A6": null,
            "A7": null
        },
        "bench": [
            null,
            null,
            null,
            null,
            null,
            null,
            null,
            null,
            null
        ],
        "teamPlan": [
            "Cho'Gath",
            "Rek'Sai",
            "Sion",
            "Gangplank",
            "Ambessa",
            "Bel'Veth",
            "Rift Herald",
            "Swain"
        ],
        "targetTeam": [],
        "autoGenerateTeam": false,
        "unlocks": [
            "Rift Herald"
        ]
    }
]